<odoo>

        <record id="view_anexo_contribuyentes_list" model="ir.ui.view">
            <field name="name">account.move.anexo.contribuyentes.list</field>
            <field name="model">account.move</field>
            <field name="arch" type="xml">
                <list string="Detalle de Anexos contribuyentes">
                    <header>
                        <button name="action_download_csv_anexo"
                                type="object"
                                string="Descargar CSV"
                                class="oe_highlight"
                                display="always"
                        />
                    </header>
                    <field name="invoice_date" string="Fecha de Emisión"/>
                    <field name="clase_documento_display" string="Clase documento"/>
                    <field name="codigo_tipo_documento_display" string="Tipo de documento"/>
                    <field name="numero_resolucion" string="Número de resolución"/>
                    <field name="hacienda_selloRecibido" string="Serie del documento"/>
                    <field name="numero_documento" string="Número de documento"/>
                    <field name="numero_control_interno" string="Número de control interno"/>
                    <field name="nit_o_nrc_anexo_contribuyentes" string="NIT o NRC del cliente"/>
                    <field name="razon_social"/>
                    <field name="total_exento"/>
                    <field name="total_no_sujeto" string="Ventas no sujetas"/>
                    <field name="total_gravado" string="Ventas grabadas locales"/>
                    <field name="debito_fiscal_contribuyentes"/>
                    <field name="ventas_cuenta_terceros"/>
                    <field name="debito_fiscal_cuenta_terceros"/>
                    <field name="total_operacion" string="Total ventas"/>
                    <field name="dui_cliente" string="DUI cliente"/>
                    <field name="tipo_operacion_display"/>
                    <field name="tipo_ingreso_display"/>
                    <field name="numero_anexo" />
                </list>
            </field>
        </record>

</odoo>